pce/__init__.py
pce/pce.py
pce/quad4pce.py
pce/util4pce.py
pce-0.1.2.dist-info/LICENSE
pce-0.1.2.dist-info/METADATA
pce-0.1.2.dist-info/WHEEL
pce-0.1.2.dist-info/top_level.txt
pce-0.1.2.dist-info/RECORD
