Metadata-Version: 2.1
Name: pce
Version: 0.1.2
Summary: Polynomial Chaos Expansion method
Home-page: https://github.com/giaccone/pce
Author: Luca Giaccone
Author-email: luca.giaccone@polito.it
License: UNKNOWN
Project-URL: example of use, https://github.com/giaccone/cogen_eval
Platform: UNKNOWN
Classifier: Programming Language :: Python :: 3
Classifier: License :: OSI Approved :: MIT License
Classifier: Operating System :: OS Independent
Requires-Python: >=3.6
License-File: LICENSE
Requires-Dist: numpy
Requires-Dist: scipy
Requires-Dist: matplotlib
Requires-Dist: joblib
